{"version":2,"kind":"Article","sha256":"b379ab9590cce432a0b175b7da061b03b9797ecf2c1fcb14c6df2b1fb2fbf4e0","slug":"index","location":"/README.md","dependencies":[],"frontmatter":{"title":"Radiative Feedback Cookbook","content_includes_title":false,"authors":[{"nameParsed":{"literal":"Project Pythia Community","given":"Project Pythia","family":"Community"},"name":"Project Pythia Community","url":"https://projectpythia.org/","id":"contributors-myst-generated-uid-0"}],"open_access":true,"license":{"content":{"id":"CC-BY-4.0","url":"https://creativecommons.org/licenses/by/4.0/","name":"Creative Commons Attribution 4.0 International","free":true,"CC":true},"code":{"id":"Apache-2.0","url":"https://opensource.org/licenses/Apache-2.0","name":"Apache License 2.0","free":true,"osi":true}},"github":"https://github.com/projectpythia/radiative-feedback-cookbook","copyright":"2024","affiliations":[{"id":"UAlbany","name":"University at Albany (SUNY)","department":"Atmospheric and Environmental Sciences","url":"https://www.albany.edu/daes"},{"id":"CISL","name":"NSF National Center for Atmospheric Research","department":"Computational and Information Systems Lab","url":"https://www.cisl.ucar.edu"},{"id":"Unidata","name":"NSF Unidata","url":"https://www.unidata.ucar.edu"},{"id":"Argonne","name":"Argonne National Laboratory","department":"Environmental Science Division","url":"https://www.anl.gov/evs"},{"id":"CarbonPlan","name":"CarbonPlan","url":"https://carbonplan.org"},{"id":"NVIDIA","name":"NVIDIA Corporation","url":"https://www.nvidia.com/"}],"edit_url":"https://github.com/projectpythia/radiative-feedback-cookbook/blob/main/README.md","thumbnail":"/radiative-feedback-cookbook/build/thumbnail-7eae567004d0efef5414a8a0f9512954.png","exports":[{"format":"md","filename":"README.md","url":"/radiative-feedback-cookbook/build/README-1d817799fe1459b7df32ce39c1708fff.md"}]},"mdast":{"type":"root","children":[{"type":"block","children":[{"type":"image","url":"/radiative-feedback-cookbook/build/thumbnail-7eae567004d0efef5414a8a0f9512954.png","alt":"thumbnail","width":500,"key":"KlA5MqphhR","urlSource":"notebooks/images/thumbnail.png"},{"type":"paragraph","position":{"start":{"line":5,"column":1},"end":{"line":7,"column":1}},"children":[{"type":"link","url":"https://github.com/ProjectPythia/radiative-feedback-cookbook/actions/workflows/nightly-build.yaml","position":{"start":{"line":5,"column":1},"end":{"line":5,"column":1}},"children":[{"type":"image","url":"/radiative-feedback-cookbook/build/69b5bebd5e3f111c78ebfda82baa5d1e.svg","alt":"nightly-build","position":{"start":{"line":5,"column":1},"end":{"line":5,"column":1}},"key":"vCMSceGFN4","urlSource":"https://github.com/ProjectPythia/radiative-feedback-cookbook/actions/workflows/nightly-build.yaml/badge.svg"}],"urlSource":"https://github.com/ProjectPythia/radiative-feedback-cookbook/actions/workflows/nightly-build.yaml","error":true,"key":"Scpfvzv6z0"},{"type":"text","value":"\n","position":{"start":{"line":5,"column":1},"end":{"line":5,"column":1}},"key":"wfJ1U5jNYR"},{"type":"link","url":"https://binder.projectpythia.org/v2/gh/ProjectPythia/radiative-feedback-cookbook/main?labpath=notebooks","position":{"start":{"line":5,"column":1},"end":{"line":5,"column":1}},"children":[{"type":"image","url":"/radiative-feedback-cookbook/build/31e3f387ea168934ca949c27e9927ea4.svg","alt":"Binder","position":{"start":{"line":5,"column":1},"end":{"line":5,"column":1}},"key":"nYyoNAFnvt","urlSource":"https://binder.projectpythia.org/badge_logo.svg"}],"urlSource":"https://binder.projectpythia.org/v2/gh/ProjectPythia/radiative-feedback-cookbook/main?labpath=notebooks","key":"vyBoSuHwYM"},{"type":"text","value":"\n","position":{"start":{"line":5,"column":1},"end":{"line":5,"column":1}},"key":"vV8ZifwkZ2"},{"type":"link","url":"https://doi.org/10.5281/zenodo.810464558","position":{"start":{"line":5,"column":1},"end":{"line":5,"column":1}},"children":[{"type":"image","url":"/radiative-feedback-cookbook/build/undefined","alt":"DOI","position":{"start":{"line":5,"column":1},"end":{"line":5,"column":1}},"key":"fmMEs4dLNb","urlSource":"https://zenodo.org/badge/810464558.svg"}],"urlSource":"https://zenodo.org/badge/latestdoi/810464558","data":{"doi":"10.5281/zenodo.810464558"},"internal":false,"protocol":"doi","key":"FiU89lER1f"}],"key":"r8wM93X1aI"},{"type":"paragraph","position":{"start":{"line":9,"column":1},"end":{"line":9,"column":1}},"children":[{"type":"text","value":"This Project Pythia Cookbook explores the fundamental science and practice of radiative feedback analysis applied to climate model output.","position":{"start":{"line":9,"column":1},"end":{"line":9,"column":1}},"key":"mthaYtJIME"}],"key":"KDDKbGpwpz"},{"type":"heading","depth":2,"position":{"start":{"line":11,"column":1},"end":{"line":11,"column":1}},"children":[{"type":"text","value":"Motivation","position":{"start":{"line":11,"column":1},"end":{"line":11,"column":1}},"key":"ND2u3DMR3J"}],"identifier":"motivation","label":"Motivation","html_id":"motivation","implicit":true,"key":"jgPTGNCAeU"},{"type":"paragraph","position":{"start":{"line":13,"column":1},"end":{"line":13,"column":1}},"children":[{"type":"text","value":"There are several well-established methods for quantifying radiative feedbacks from climate model output, and these have been widely used in the scientific literature. However, a comprehensive set of tutorials representing best practices for implementing these methods has been lacking, forcing new practioners to “reinvent the wheel” and piece together the implementation details from sometimes incomplete descriptions in the primary literature.","position":{"start":{"line":13,"column":1},"end":{"line":13,"column":1}},"key":"HwnpRDWPAv"}],"key":"w76WkEGjf6"},{"type":"paragraph","position":{"start":{"line":15,"column":1},"end":{"line":15,"column":1}},"children":[{"type":"text","value":"This Cookbook aims to fill this gap by collecting a verbose set of tutorials that take the reader through some of the basic theory and implementation details, with plentiful example code that can be easily adapted to new datasets and new research applications. The examples will skew heavily toward the method of ","position":{"start":{"line":15,"column":1},"end":{"line":15,"column":1}},"key":"ZputxC1Lo9"},{"type":"emphasis","position":{"start":{"line":15,"column":1},"end":{"line":15,"column":1}},"children":[{"type":"text","value":"radiative kernels","position":{"start":{"line":15,"column":1},"end":{"line":15,"column":1}},"key":"Kw7NGziIPj"}],"key":"x42qCnUJeK"},{"type":"text","value":", with some comparison to other methods.","position":{"start":{"line":15,"column":1},"end":{"line":15,"column":1}},"key":"HqhZ24X0Pk"}],"key":"R1kycBG5aA"},{"type":"heading","depth":2,"position":{"start":{"line":17,"column":1},"end":{"line":17,"column":1}},"children":[{"type":"text","value":"Authors","position":{"start":{"line":17,"column":1},"end":{"line":17,"column":1}},"key":"RG3B1MRdCM"}],"identifier":"authors","label":"Authors","html_id":"authors","implicit":true,"key":"J4bnKvqd3s"},{"type":"paragraph","position":{"start":{"line":19,"column":1},"end":{"line":19,"column":1}},"children":[{"type":"link","url":"https://github.com/brian-rose","position":{"start":{"line":19,"column":1},"end":{"line":19,"column":1}},"children":[{"type":"text","value":"Brian Rose","position":{"start":{"line":19,"column":1},"end":{"line":19,"column":1}},"key":"oy21bH2yB1"}],"urlSource":"https://github.com/brian-rose","error":true,"key":"xvSV92GSHN"},{"type":"text","value":", ","position":{"start":{"line":19,"column":1},"end":{"line":19,"column":1}},"key":"vN58YU87jL"},{"type":"link","url":"https://github.com/rytam2","position":{"start":{"line":19,"column":1},"end":{"line":19,"column":1}},"children":[{"type":"text","value":"Rachel Tam","position":{"start":{"line":19,"column":1},"end":{"line":19,"column":1}},"key":"a8iarZPi7e"}],"urlSource":"https://github.com/rytam2","error":true,"key":"qr9G4JhoPi"},{"type":"text","value":", ","position":{"start":{"line":19,"column":1},"end":{"line":19,"column":1}},"key":"cbFAp7Lg6p"},{"type":"link","url":"https://github.com/tyfolino","position":{"start":{"line":19,"column":1},"end":{"line":19,"column":1}},"children":[{"type":"text","value":"Ty Janoski","position":{"start":{"line":19,"column":1},"end":{"line":19,"column":1}},"key":"ke7G1HbGJp"}],"urlSource":"https://github.com/tyfolino","error":true,"key":"uAzum4dQ1v"},{"type":"text","value":", ","position":{"start":{"line":19,"column":1},"end":{"line":19,"column":1}},"key":"zJc0IhqfB7"},{"type":"link","url":"https://github.com/r-ford","position":{"start":{"line":19,"column":1},"end":{"line":19,"column":1}},"children":[{"type":"text","value":"Robert Ford","position":{"start":{"line":19,"column":1},"end":{"line":19,"column":1}},"key":"gue8H5iaCs"}],"urlSource":"https://github.com/r-ford","error":true,"key":"mQMJgyWNP9"},{"type":"text","value":", ","position":{"start":{"line":19,"column":1},"end":{"line":19,"column":1}},"key":"fVupl6HHWS"},{"type":"link","url":"https://github.com/hannahzafar","position":{"start":{"line":19,"column":1},"end":{"line":19,"column":1}},"children":[{"type":"text","value":"Hannah Zafar","position":{"start":{"line":19,"column":1},"end":{"line":19,"column":1}},"key":"EI8Ound6Ll"}],"urlSource":"https://github.com/hannahzafar","error":true,"key":"JAeiUIOPPt"},{"type":"text","value":", ","position":{"start":{"line":19,"column":1},"end":{"line":19,"column":1}},"key":"v7fX2Re2Cl"},{"type":"link","url":"https://github.com/anacmontoya","position":{"start":{"line":19,"column":1},"end":{"line":19,"column":1}},"children":[{"type":"text","value":"Ana Castaneda Montoya","position":{"start":{"line":19,"column":1},"end":{"line":19,"column":1}},"key":"dkfjP7F9yd"}],"urlSource":"https://github.com/anacmontoya","error":true,"key":"jWv4GlmDYZ"},{"type":"text","value":", and ","position":{"start":{"line":19,"column":1},"end":{"line":19,"column":1}},"key":"JwchHvzN3S"},{"type":"link","url":"https://github.com/kathrynrooney","position":{"start":{"line":19,"column":1},"end":{"line":19,"column":1}},"children":[{"type":"text","value":"Kathryn Rooney","position":{"start":{"line":19,"column":1},"end":{"line":19,"column":1}},"key":"fG7aKGcwY4"}],"urlSource":"https://github.com/kathrynrooney","error":true,"key":"EZDC4C5Bqm"}],"key":"XTp5104pxs"},{"type":"heading","depth":3,"position":{"start":{"line":21,"column":1},"end":{"line":21,"column":1}},"children":[{"type":"text","value":"Contributors","position":{"start":{"line":21,"column":1},"end":{"line":21,"column":1}},"key":"ctCP22OoBK"}],"identifier":"contributors","label":"Contributors","html_id":"contributors","implicit":true,"key":"Z9mXo1GT1b"},{"type":"link","url":"https://github.com/ProjectPythia/radiative-feedback-cookbook/graphs/contributors","children":[{"type":"image","url":"/radiative-feedback-cookbook/build/8dee8a4cebc60b94b95a04bfa51938cb.svg","key":"SJ2L64InmR","urlSource":"https://contrib.rocks/image?repo=ProjectPythia/radiative-feedback-cookbook"}],"urlSource":"https://github.com/ProjectPythia/radiative-feedback-cookbook/graphs/contributors","error":true,"key":"AuCwHsBus1"},{"type":"heading","depth":2,"position":{"start":{"line":27,"column":1},"end":{"line":27,"column":1}},"children":[{"type":"text","value":"Structure","position":{"start":{"line":27,"column":1},"end":{"line":27,"column":1}},"key":"xB561rlEhT"}],"identifier":"structure","label":"Structure","html_id":"structure","implicit":true,"key":"L5JE3mfvUx"},{"type":"paragraph","position":{"start":{"line":29,"column":1},"end":{"line":29,"column":1}},"children":[{"type":"text","value":"This Cookbook is organized as follows:","position":{"start":{"line":29,"column":1},"end":{"line":29,"column":1}},"key":"INQhAmQ7zA"}],"key":"AMvyPr8zme"},{"type":"heading","depth":3,"position":{"start":{"line":31,"column":1},"end":{"line":31,"column":1}},"children":[{"type":"text","value":"Foundations","position":{"start":{"line":31,"column":1},"end":{"line":31,"column":1}},"key":"HE7RdGgKae"}],"identifier":"foundations","label":"Foundations","html_id":"foundations","implicit":true,"key":"g1XQrSfAwT"},{"type":"paragraph","position":{"start":{"line":33,"column":1},"end":{"line":33,"column":1}},"children":[{"type":"text","value":"This section takes the reader through some of the basic ideas and provides an overview of the mathematical theory underlying the radiative kernel method.","position":{"start":{"line":33,"column":1},"end":{"line":33,"column":1}},"key":"pCSNBnAnfk"}],"key":"trLIxehctD"},{"type":"heading","depth":3,"position":{"start":{"line":35,"column":1},"end":{"line":35,"column":1}},"children":[{"type":"text","value":"Feedback Analysis","position":{"start":{"line":35,"column":1},"end":{"line":35,"column":1}},"key":"sfdRu6P0gK"}],"identifier":"feedback-analysis","label":"Feedback Analysis","html_id":"feedback-analysis","implicit":true,"key":"Z6kNyljvSL"},{"type":"paragraph","position":{"start":{"line":37,"column":1},"end":{"line":37,"column":1}},"children":[{"type":"text","value":"This section links the theory to the practice by demonstrating the detailed implementation of some radiative feedback calculations.","position":{"start":{"line":37,"column":1},"end":{"line":37,"column":1}},"key":"LROF0G5nGW"}],"key":"XCpcJ6ElwW"},{"type":"heading","depth":3,"position":{"start":{"line":39,"column":1},"end":{"line":39,"column":1}},"children":[{"type":"text","value":"Simplifying Calculations","position":{"start":{"line":39,"column":1},"end":{"line":39,"column":1}},"key":"sHyY2gkU25"}],"identifier":"simplifying-calculations","label":"Simplifying Calculations","html_id":"simplifying-calculations","implicit":true,"key":"I5O7UlnnXu"},{"type":"paragraph","position":{"start":{"line":41,"column":1},"end":{"line":41,"column":1}},"children":[{"type":"text","value":"This section gives more practical example code for carrying out feedback calculations on CMIP6 data, making use of some specialized software packages.","position":{"start":{"line":41,"column":1},"end":{"line":41,"column":1}},"key":"qr6uhaDbbj"}],"key":"CcW0ansvQF"},{"type":"heading","depth":2,"position":{"start":{"line":43,"column":1},"end":{"line":43,"column":1}},"children":[{"type":"text","value":"Running the Notebooks","position":{"start":{"line":43,"column":1},"end":{"line":43,"column":1}},"key":"yCRVxBCR8V"}],"identifier":"running-the-notebooks","label":"Running the Notebooks","html_id":"running-the-notebooks","implicit":true,"key":"epApxR8bHy"},{"type":"paragraph","position":{"start":{"line":45,"column":1},"end":{"line":45,"column":1}},"children":[{"type":"text","value":"You can either run the notebook using ","position":{"start":{"line":45,"column":1},"end":{"line":45,"column":1}},"key":"rRyfLKMeQe"},{"type":"link","url":"https://binder.projectpythia.org/","position":{"start":{"line":45,"column":1},"end":{"line":45,"column":1}},"children":[{"type":"text","value":"Binder","position":{"start":{"line":45,"column":1},"end":{"line":45,"column":1}},"key":"iU5XTKOJMG"}],"urlSource":"https://binder.projectpythia.org/","key":"m9HEWuGQt0"},{"type":"text","value":" or on your local machine.","position":{"start":{"line":45,"column":1},"end":{"line":45,"column":1}},"key":"rPKoZjpGdD"}],"key":"HSro5JfBEg"},{"type":"heading","depth":3,"position":{"start":{"line":47,"column":1},"end":{"line":47,"column":1}},"children":[{"type":"text","value":"Running on Binder","position":{"start":{"line":47,"column":1},"end":{"line":47,"column":1}},"key":"f2XNZNOPiW"}],"identifier":"running-on-binder","label":"Running on Binder","html_id":"running-on-binder","implicit":true,"key":"O7itUn3flE"},{"type":"paragraph","position":{"start":{"line":49,"column":1},"end":{"line":62,"column":1}},"children":[{"type":"text","value":"The simplest way to interact with a Jupyter Notebook is through\n","position":{"start":{"line":49,"column":1},"end":{"line":49,"column":1}},"key":"TKAYJrZHcL"},{"type":"link","url":"https://binder.projectpythia.org/","position":{"start":{"line":49,"column":1},"end":{"line":49,"column":1}},"children":[{"type":"text","value":"Binder","position":{"start":{"line":49,"column":1},"end":{"line":49,"column":1}},"key":"fy1miiRVDa"}],"urlSource":"https://binder.projectpythia.org/","key":"ZcjXR1fSgz"},{"type":"text","value":", which enables the execution of a\n","position":{"start":{"line":49,"column":1},"end":{"line":49,"column":1}},"key":"Tr4aGsIA31"},{"type":"link","url":"https://jupyterbook.org","position":{"start":{"line":49,"column":1},"end":{"line":49,"column":1}},"children":[{"type":"text","value":"Jupyter Book","position":{"start":{"line":49,"column":1},"end":{"line":49,"column":1}},"key":"pjjwL8FJsK"}],"urlSource":"https://jupyterbook.org","key":"J33uCFyNf7"},{"type":"text","value":" in the cloud. The details of how this works are not\nimportant for now. All you need to know is how to launch a Pythia\nCookbooks chapter via Binder. Simply navigate your mouse to\nthe top right corner of the book chapter you are viewing and click\non the rocket ship icon, (see figure below), and be sure to select\n“launch Binder”. After a moment you should be presented with a\nnotebook that you can interact with. I.e. you’ll be able to execute\nand even change the example programs. You’ll see that the code cells\nhave no output at first, until you execute them by pressing\n","position":{"start":{"line":49,"column":1},"end":{"line":49,"column":1}},"key":"DGw9809NSq"},{"type":"keyboard","children":[{"type":"text","value":"Shift","key":"iQwdYp8APm"}],"key":"Rb09JbT9GT"},{"type":"text","value":"+","position":{"start":{"line":49,"column":1},"end":{"line":49,"column":1}},"key":"QgvRui2bAa"},{"type":"keyboard","children":[{"type":"text","value":"Enter","key":"FavsE1NgIn"}],"key":"h6VKmdu61Z"},{"type":"text","value":". Complete details on how to interact with\na live Jupyter notebook are described in ","position":{"start":{"line":49,"column":1},"end":{"line":49,"column":1}},"key":"U28FMI3nly"},{"type":"link","url":"https://foundations.projectpythia.org/foundations/getting-started-jupyter","position":{"start":{"line":49,"column":1},"end":{"line":49,"column":1}},"children":[{"type":"text","value":"Getting Started with\nJupyter","position":{"start":{"line":49,"column":1},"end":{"line":49,"column":1}},"key":"cl3put6ZLL"}],"urlSource":"https://foundations.projectpythia.org/foundations/getting-started-jupyter","key":"ZXejEHIXlk"},{"type":"text","value":".","position":{"start":{"line":49,"column":1},"end":{"line":49,"column":1}},"key":"wMbdsqhgdI"}],"key":"s40Yta6hOs"},{"type":"heading","depth":3,"position":{"start":{"line":64,"column":1},"end":{"line":64,"column":1}},"children":[{"type":"text","value":"Running on Your Own Machine","position":{"start":{"line":64,"column":1},"end":{"line":64,"column":1}},"key":"opEIk0LhXE"}],"identifier":"running-on-your-own-machine","label":"Running on Your Own Machine","html_id":"running-on-your-own-machine","implicit":true,"key":"mgdVZbSXZq"},{"type":"paragraph","position":{"start":{"line":66,"column":1},"end":{"line":66,"column":1}},"children":[{"type":"text","value":"If you are interested in running this material locally on your computer, you will need to follow this workflow:","position":{"start":{"line":66,"column":1},"end":{"line":66,"column":1}},"key":"KXSXlqVr1c"}],"key":"JZ2mDDHsx6"},{"type":"list","ordered":true,"start":1,"spread":false,"position":{"start":{"line":68,"column":1},"end":{"line":87,"column":1}},"children":[{"type":"listItem","spread":true,"position":{"start":{"line":68,"column":1},"end":{"line":73,"column":1}},"children":[{"type":"paragraph","position":{"start":{"line":68,"column":1},"end":{"line":68,"column":1}},"children":[{"type":"text","value":"Clone the ","position":{"start":{"line":68,"column":1},"end":{"line":68,"column":1}},"key":"wDaHYMfRZG"},{"type":"inlineCode","value":"https://github.com/ProjectPythia/radiative-feedback-cookbook","position":{"start":{"line":68,"column":1},"end":{"line":68,"column":1}},"key":"SK8QF9IPIn"},{"type":"text","value":" repository:","position":{"start":{"line":68,"column":1},"end":{"line":68,"column":1}},"key":"so1DfcynMh"}],"key":"jIiIJ5YzVW"},{"type":"code","lang":"bash","value":" git clone https://github.com/ProjectPythia/radiative-feedback-cookbook.git","position":{"start":{"line":70,"column":1},"end":{"line":72,"column":1}},"key":"sVzTzoffXI"}],"key":"LsEkHZebFf"},{"type":"listItem","spread":true,"position":{"start":{"line":74,"column":1},"end":{"line":77,"column":1}},"children":[{"type":"paragraph","position":{"start":{"line":74,"column":1},"end":{"line":74,"column":1}},"children":[{"type":"text","value":"Move into the ","position":{"start":{"line":74,"column":1},"end":{"line":74,"column":1}},"key":"zXCIo52e2f"},{"type":"inlineCode","value":"radiative-feedback-cookbook","position":{"start":{"line":74,"column":1},"end":{"line":74,"column":1}},"key":"iCwwyuPfnd"},{"type":"text","value":" directory","position":{"start":{"line":74,"column":1},"end":{"line":74,"column":1}},"key":"FSReb7LPne"}],"key":"mVCLPOFLGN"},{"type":"code","lang":"bash","value":"cd radiative-feedback-cookbook","position":{"start":{"line":75,"column":1},"end":{"line":77,"column":1}},"key":"VcZYq2KIKC"}],"key":"oQMyLU72AY"},{"type":"listItem","spread":true,"position":{"start":{"line":78,"column":1},"end":{"line":82,"column":1}},"children":[{"type":"paragraph","position":{"start":{"line":78,"column":1},"end":{"line":78,"column":1}},"children":[{"type":"text","value":"Create and activate your conda environment from the ","position":{"start":{"line":78,"column":1},"end":{"line":78,"column":1}},"key":"G1UUEeEhPi"},{"type":"inlineCode","value":"environment.yml","position":{"start":{"line":78,"column":1},"end":{"line":78,"column":1}},"key":"ZsmOoRMTan"},{"type":"text","value":" file","position":{"start":{"line":78,"column":1},"end":{"line":78,"column":1}},"key":"y4XHe98ZTe"}],"key":"MwWADsRcHm"},{"type":"code","lang":"bash","value":"conda env create -f environment.yml\nconda activate feedback-cookbook-dev","position":{"start":{"line":79,"column":1},"end":{"line":82,"column":1}},"key":"SpxM8Jz6LC"}],"key":"RZxF4At5K7"},{"type":"listItem","spread":true,"position":{"start":{"line":83,"column":1},"end":{"line":87,"column":1}},"children":[{"type":"paragraph","position":{"start":{"line":83,"column":1},"end":{"line":83,"column":1}},"children":[{"type":"text","value":"Move into the ","position":{"start":{"line":83,"column":1},"end":{"line":83,"column":1}},"key":"J6Op8hNuC9"},{"type":"inlineCode","value":"notebooks","position":{"start":{"line":83,"column":1},"end":{"line":83,"column":1}},"key":"UtpNORwJft"},{"type":"text","value":" directory and start up Jupyterlab","position":{"start":{"line":83,"column":1},"end":{"line":83,"column":1}},"key":"aisDkwHhnA"}],"key":"ay9qQPZm9c"},{"type":"code","lang":"bash","value":"cd notebooks/\njupyter lab","position":{"start":{"line":84,"column":1},"end":{"line":87,"column":1}},"key":"wBSEbzIY3e"}],"key":"aafiexvdM3"}],"key":"hEarspObuK"}],"key":"Pm2mPMOo8W"}],"key":"gCnMIJddjy"},"references":{"cite":{"order":[],"data":{}}},"footer":{"navigation":{"next":{"title":"How to Cite This Cookbook","url":"/notebooks/how-to-cite","group":"Preamble"}}},"domain":"http://localhost:3000"}